nspawn/__init__.py
nspawn/config.ini
nspawn/app/__init__.py
nspawn/app/engine/__init__.py
nspawn/app/engine/build.py
nspawn/app/engine/invoke.py
nspawn/app/engine/main.py
nspawn/app/engine/parser.py
nspawn/app/engine/setup.py
nspawn/app/hatcher/__init__.py
nspawn/app/hatcher/main.py
nspawn/app/hatcher/parser.py
nspawn/app/hatcher/service/__init__.py
nspawn/app/hatcher/service/image-proxy/arkon.py
nspawn/app/hatcher/service/image-proxy/build.py
nspawn/app/hatcher/service/image-proxy/readme.md
nspawn/app/hatcher/service/image-proxy/setup.py
nspawn/app/hatcher/service/image-proxy/unsetup.py
nspawn/app/hatcher/service/image-proxy/etc/hostname
nspawn/app/hatcher/service/image-proxy/etc/inittab
nspawn/app/hatcher/service/image-proxy/etc/motd
nspawn/app/hatcher/service/image-proxy/etc/network/interfaces
nspawn/app/hatcher/service/image-proxy/etc/squid/squid.conf
nspawn/app/hatcher/service/image-proxy/etc/squid/store_id_prog.py
nspawn/app/hatcher/service/image-proxy/etc/squid/store_id_test.py
nspawn/app/hatcher/service/image-proxy/etc/squid/ca/proxy-cert.pem
nspawn/app/hatcher/service/image-proxy/etc/squid/ca/proxy-key.pem
nspawn/app/hatcher/service/image-proxy/etc/squid/ca/readme.md
nspawn/app/hatcher/service/image-proxy/etc/squid/script/store_id_prog.py
nspawn/app/hatcher/service/image-proxy/etc/squid/script/store_id_prog.sh
nspawn/app/hatcher/service/image-proxy/etc/squid/script/store_id_test.py
nspawn/app/hatcher/service/image-proxy/etc/squid/script/store_id_test.sh
nspawn/app/hatcher/service/image-proxy/root/readme.md
nspawn/app/hatcher/service/image-proxy/root/.config/readme.md
nspawn/app/hatcher/service/image-proxy/root/.config/htop/htoprc
nspawn/app/hatcher/service/image-proxy/root/.config/mc/ini
nspawn/app/hatcher/service/image-proxy/root/.config/mc/panels.ini
nspawn/app/hatcher/service/image-proxy/root/.ssh/readme.md
nspawn/app/hatcher/service/image-server/arkon.py
nspawn/app/hatcher/service/image-server/build.py
nspawn/app/hatcher/service/image-server/readme.md
nspawn-0.8.4.dist-info/METADATA
nspawn-0.8.4.dist-info/WHEEL
nspawn-0.8.4.dist-info/entry_points.txt
nspawn-0.8.4.dist-info/top_level.txt
nspawn-0.8.4.dist-info/RECORD
