Metadata-Version: 2.2
Name: nspawn
Version: 0.8.4
Summary: Containers with systemd-nspawn
Author-email: Andrei Pozolotin <andrei.pozolotin@gmail.com>
License:                                  Apache License
Project-URL: Source, https://github.com/random-python/nspawn
Project-URL: Homepage, https://github.com/random-python/nspawn
Project-URL: Documentation, https://github.com/random-python/nspawn
Keywords: nspawn,container,systemd,systemd-nspawn
Classifier: Development Status :: 4 - Beta
Classifier: Environment :: Console
Classifier: Intended Audience :: Developers
Classifier: Intended Audience :: Information Technology
Classifier: Intended Audience :: System Administrators
Classifier: License :: OSI Approved :: Apache Software License
Classifier: Operating System :: POSIX :: Linux
Classifier: Topic :: System :: Systems Administration
Classifier: Topic :: Terminals
Classifier: Topic :: Utilities
Classifier: Programming Language :: Python
Classifier: Programming Language :: Python :: 3 :: Only
Classifier: Programming Language :: Python :: 3.11
Classifier: Programming Language :: Python :: 3.12
Classifier: Programming Language :: Python :: 3.13
Classifier: Topic :: Utilities
Requires-Python: >=3.11
Requires-Dist: pyyaml>=6
Requires-Dist: jinja2>=3
Provides-Extra: test
Requires-Dist: tox; extra == "test"
Requires-Dist: pytest; extra == "test"
